pyuavcan/VERSION
pyuavcan/__init__.py
pyuavcan/application/__init__.py
pyuavcan/application/_node.py
pyuavcan/application/_node_factory.py
pyuavcan/application/_port_list_publisher.py
pyuavcan/application/_register_server.py
pyuavcan/application/_registry_factory.py
pyuavcan/application/_transport_factory.py
pyuavcan/application/diagnostic.py
pyuavcan/application/file.py
pyuavcan/application/heartbeat_publisher.py
pyuavcan/application/node_tracker.py
pyuavcan/application/plug_and_play.py
pyuavcan/application/register/__init__.py
pyuavcan/application/register/_registry.py
pyuavcan/application/register/_value.py
pyuavcan/application/register/backend/__init__.py
pyuavcan/application/register/backend/dynamic.py
pyuavcan/application/register/backend/static.py
pyuavcan/dsdl/__init__.py
pyuavcan/dsdl/_builtin_form.py
pyuavcan/dsdl/_compiler.py
pyuavcan/dsdl/_composite_object.py
pyuavcan/dsdl/_serialized_representation/__init__.py
pyuavcan/dsdl/_serialized_representation/_common.py
pyuavcan/dsdl/_serialized_representation/_deserializer.py
pyuavcan/dsdl/_serialized_representation/_serializer.py
pyuavcan/dsdl/_templates/DelimitedType.j2
pyuavcan/dsdl/_templates/Namespace.j2
pyuavcan/dsdl/_templates/ServiceType.j2
pyuavcan/dsdl/_templates/StructureType.j2
pyuavcan/dsdl/_templates/UnionType.j2
pyuavcan/dsdl/_templates/base.j2
pyuavcan/dsdl/_templates/deserialization.j2
pyuavcan/dsdl/_templates/serialization.j2
pyuavcan/presentation/__init__.py
pyuavcan/presentation/_presentation.py
pyuavcan/presentation/_port/__init__.py
pyuavcan/presentation/_port/_base.py
pyuavcan/presentation/_port/_client.py
pyuavcan/presentation/_port/_error.py
pyuavcan/presentation/_port/_publisher.py
pyuavcan/presentation/_port/_server.py
pyuavcan/presentation/_port/_subscriber.py
pyuavcan/transport/__init__.py
pyuavcan/transport/_data_specifier.py
pyuavcan/transport/_error.py
pyuavcan/transport/_payload_metadata.py
pyuavcan/transport/_session.py
pyuavcan/transport/_timestamp.py
pyuavcan-1.4.5.dist-info/LICENSE
pyuavcan-1.4.5.dist-info/METADATA
pyuavcan-1.4.5.dist-info/WHEEL
pyuavcan-1.4.5.dist-info/top_level.txt
pyuavcan-1.4.5.dist-info/RECORD
