Metadata-Version: 2.1
Name: pyuavcan
Version: 1.4.5
Summary: A full-featured implementation of the UAVCAN protocol stack in Python.
Home-page: https://uavcan.org
Author: UAVCAN Consortium
Author-email: consortium@uavcan.org
License: MIT
Keywords: uavcan,pub-sub,publish-subscribe,data-bus,can-bus,ethernet,vehicular,onboard-networking,avionics,communication-protocol,broker
Platform: UNKNOWN
Classifier: Intended Audience :: Developers
Classifier: Topic :: Scientific/Engineering
Classifier: Topic :: Software Development :: Embedded Systems
Classifier: Topic :: Software Development :: Libraries :: Python Modules
Classifier: Topic :: Software Development :: Object Brokering
Classifier: Topic :: System :: Distributed Computing
Classifier: Topic :: System :: Networking
Classifier: License :: OSI Approved :: MIT License
Classifier: Programming Language :: Python
Classifier: Programming Language :: Python :: 3
Classifier: Operating System :: OS Independent
Classifier: Typing :: Typed
License-File: LICENSE
Requires-Dist: nunavut (~=1.6)
Requires-Dist: numpy (~=1.21)
Provides-Extra: transport-can-pythoncan
Requires-Dist: python-can[serial] (~=3.3) ; extra == 'transport-can-pythoncan'
Provides-Extra: transport-serial
Requires-Dist: pyserial (~=3.5) ; extra == 'transport-serial'
Requires-Dist: cobs (~=1.1.4) ; extra == 'transport-serial'
Provides-Extra: transport-udp
Requires-Dist: libpcap (<2.0.0,>=1.11.0b2) ; extra == 'transport-udp'
